nmspy/__init__.py
nmspy/caching.py
nmspy/common.py
nmspy/decorators.py
nmspy/engine.py
nmspy/globals.py
nmspy/pymhf.toml
nmspy/terminal_parser.py
nmspy/_internal_mods/singletons.py
nmspy/_internal_mods/textChatManager.py
nmspy/data/audiokinetic.py
nmspy/data/basic_types.py
nmspy/data/exported_types.py
nmspy/data/nanovg.py
nmspy/data/types.py
nmspy/data/enums/__init__.py
nmspy/data/enums/external_enums.py
nmspy/data/enums/internal_enums.py
nmspy-157371.0.dist-info/licenses/LICENSE
nmspy-157371.0.dist-info/METADATA
nmspy-157371.0.dist-info/WHEEL
nmspy-157371.0.dist-info/entry_points.txt
nmspy-157371.0.dist-info/top_level.txt
nmspy-157371.0.dist-info/RECORD
