Metadata-Version: 2.4
Name: NMSpy
Version: 157371.0
Summary: No Man's Sky python modding API
Author: monkeyman192
Maintainer: monkeyman192
License-Expression: MIT
Project-URL: Homepage, https://github.com/monkeyman192/NMS.py
Project-URL: Repository, https://github.com/monkeyman192/NMS.py.git
Keywords: hooking,games,hacking,modding
Classifier: Development Status :: 3 - Alpha
Classifier: Environment :: Win32 (MS Windows)
Classifier: Operating System :: Microsoft
Classifier: Programming Language :: Python :: 3.9
Classifier: Programming Language :: Python :: 3.10
Classifier: Programming Language :: Python :: 3.11
Classifier: Programming Language :: Python :: 3.12
Classifier: Programming Language :: Python :: 3.13
Classifier: Programming Language :: Python :: 3 :: Only
Requires-Python: <4,>=3.9
License-File: LICENSE
Requires-Dist: pymhf[gui]>=0.2.1
Dynamic: license-file
